python_framework/__init__.py
python_framework/config.py
python_framework/logger.py
python_framework/main.py
shanx_framework-0.1.6.dist-info/entry_points.txt
shanx_framework-0.1.6.dist-info/LICENSE
shanx_framework-0.1.6.dist-info/WHEEL
shanx_framework-0.1.6.dist-info/METADATA
shanx_framework-0.1.6.dist-info/RECORD
