Metadata-Version: 2.1
Name: shanx-framework
Version: 0.1.6
Summary: Python Framework
Home-page: https://github.com/sp-95/python-framework
License: BSD
Keywords: cookiecutter,template,package
Author: Shashanka Prajapati
Author-email: shashankap95@gmail.com
Requires-Python: >=3.7,<4.0
Classifier: Development Status :: 4 - Beta
Classifier: Environment :: Console
Classifier: Intended Audience :: Developers
Classifier: License :: OSI Approved :: BSD License
Classifier: License :: Other/Proprietary License
Classifier: Natural Language :: English
Classifier: Programming Language :: Python
Classifier: Programming Language :: Python :: 3
Classifier: Programming Language :: Python :: 3.7
Classifier: Programming Language :: Python :: 3.8
Classifier: Programming Language :: Python :: 3.9
Classifier: Programming Language :: Python :: 3.10
Classifier: Programming Language :: Python :: 3
Classifier: Programming Language :: Python :: 3 :: Only
Classifier: Programming Language :: Python :: 3.7
Classifier: Programming Language :: Python :: 3.8
Classifier: Topic :: Software Development
Requires-Dist: cookiecutter
Requires-Dist: dynaconf
Requires-Dist: fire
Requires-Dist: loguru
Requires-Dist: termcolor
Requires-Dist: toml
Project-URL: Bug Tracker, https://github.com/sp-95/python-framework/issues
Project-URL: Documentation, https://sp-95.github.io/python-framework
Project-URL: Repository, https://github.com/sp-95/python-framework
